jsonsqlquery/__init__.py
jsonsqlquery/cli.py
jsonsqlquery/core.py
jsonsqlquery-0.1.2.dist-info/LICENSE
jsonsqlquery-0.1.2.dist-info/METADATA
jsonsqlquery-0.1.2.dist-info/WHEEL
jsonsqlquery-0.1.2.dist-info/entry_points.txt
jsonsqlquery-0.1.2.dist-info/RECORD
