Metadata-Version: 2.1
Name: jsonsqlquery
Version: 0.1.2
Summary: Query JSON using SQL
License: MIT
Author: Peter Byfield
Author-email: byfield554@gmail.com
Requires-Python: >=3.10,<4.0
Classifier: License :: OSI Approved :: MIT License
Classifier: Programming Language :: Python :: 3
Classifier: Programming Language :: Python :: 3.10
Classifier: Programming Language :: Python :: 3.11
